README.md
setup.py
zhang_hello/__init__.py
zhang_hello/hello.py
zhang_hello.egg-info/PKG-INFO
zhang_hello.egg-info/SOURCES.txt
zhang_hello.egg-info/dependency_links.txt
zhang_hello.egg-info/top_level.txt