Metadata-Version: 2.1
Name: zhang-hello
Version: 1.0.1
Summary: My first setup files
Home-page: UNKNOWN
Author: Zhang
License: MIT
Platform: UNKNOWN
